pypeloton/__init__.py
pypeloton/const.py
pypeloton/helpers.py
pypeloton/pypeloton.py
pypeloton/utils.py
pypeloton/version.py
pypeloton-0.1.1.dist-info/LICENSE
pypeloton-0.1.1.dist-info/METADATA
pypeloton-0.1.1.dist-info/WHEEL
pypeloton-0.1.1.dist-info/top_level.txt
pypeloton-0.1.1.dist-info/RECORD
