Metadata-Version: 2.1
Name: pypeloton
Version: 0.1.1
Summary: Client library for the Peloton API
Home-page: https://github.com/raman325/pypeloton
Author: raman325
Author-email: raman325@gmail.com
License: MIT
Keywords: peloton
Platform: UNKNOWN
Classifier: Development Status :: 2 - Pre-Alpha
Classifier: Intended Audience :: Developers
Classifier: License :: OSI Approved :: GNU General Public License v3 (GPLv3)
Classifier: Programming Language :: Python :: 3.7
Requires-Python: >=3.6
Requires-Dist: aiohttp
